flask_routes.py
flask_routes-0.1.0.dist-info/DESCRIPTION.rst
flask_routes-0.1.0.dist-info/METADATA
flask_routes-0.1.0.dist-info/RECORD
flask_routes-0.1.0.dist-info/WHEEL
flask_routes-0.1.0.dist-info/entry_points.txt
flask_routes-0.1.0.dist-info/metadata.json
flask_routes-0.1.0.dist-info/top_level.txt
